hello.py
powerleone.py
energicity-0.0.10.3.dist-info/LICENSE.txt
energicity-0.0.10.3.dist-info/METADATA
energicity-0.0.10.3.dist-info/WHEEL
energicity-0.0.10.3.dist-info/top_level.txt
energicity-0.0.10.3.dist-info/RECORD
