Metadata-Version: 2.1
Name: energicity
Version: 0.0.10.3
Summary: EnergiCity main python package, it's a toolkit
Home-page: https://gitlab.com/EnergiCity/energicity-py-package
Author: Ahmed Ali
Author-email: ahmed.elsir.khalfalla@gmail.com
License: UNKNOWN
Platform: UNKNOWN
Requires-Dist: requests
